{"examples_hello.md":"BdZ-cojn","api_usewebrtc.md":"IMpG0-lx","api_index.md":"Bit91NOR","api_vue_usearray.md":"BbM3UL34","api_vue_userecord.md":"aWdknB_H","api_usemap.md":"DV5o-xlg","api_vue_usemapref.md":"5T9QNrrn","api_usearrayref.md":"D6uHM3L7","api_vue_usearrayref.md":"CRV6U3L1","api_vue_userecordref.md":"BwI2Nrim","changelog.md":"-BqWhyPB","examples_simple-list.md":"BRAXvEcC","api_vue_usemap.md":"Bv6gIXKv","examples_cursor.md":"hVa27Hqe","index.md":"h-xEhzsf","api_vue_usewebrtc.md":"DpH9Y_yD","examples_index.md":"BBt4GMxk","api_usearray.md":"EpkZjMjp"}
